{
  "__className__": "serverpod.DatabaseDefinition",
  "moduleName": "echomirror_server",
  "tables": [
    {
      "__className__": "serverpod.TableDefinition",
      "name": "log_entries",
      "dartName": "LogEntry",
      "module": "echomirror_server",
      "schema": "public",
      "columns": [
        {
          "__className__": "serverpod.ColumnDefinition",
          "name": "id",
          "columnType": 6,
          "isNullable": false,
          "columnDefault": "nextval('log_entries_id_seq'::regclass)",
          "dartType": "int?"
        },
        {
          "__className__": "serverpod.ColumnDefinition",
          "name": "userId",
          "columnType": 0,
          "isNullable": false,
          "dartType": "String"
        },
        {
          "__className__": "serverpod.ColumnDefinition",
          "name": "date",
          "columnType": 4,
          "isNullable": false,
          "dartType": "DateTime"
        },
        {
          "__className__": "serverpod.ColumnDefinition",
          "name": "mood",
          "columnType": 6,
          "isNullable": true,
          "dartType": "int?"
        },
        {
          "__className__": "serverpod.ColumnDefinition",
          "name": "habits",
          "columnType": 8,
          "isNullable": false,
          "dartType": "List<String>"
        },
        {
          "__className__": "serverpod.ColumnDefinition",
          "name": "notes",
          "columnType": 0,
          "isNullable": true,
          "dartType": "String?"
        },
        {
          "__className__": "serverpod.ColumnDefinition",
          "name": "createdAt",
          "columnType": 4,
          "isNullable": false,
          "dartType": "DateTime"
        },
        {
          "__className__": "serverpod.ColumnDefinition",
          "name": "updatedAt",
          "columnType": 4,
          "isNullable": true,
          "dartType": "DateTime?"
        }
      ],
      "foreignKeys": [],
      "indexes": [
        {
          "__className__": "serverpod.IndexDefinition",
          "indexName": "log_entries_pkey",
          "elements": [
            {
              "__className__": "serverpod.IndexElementDefinition",
              "type": 0,
              "definition": "id"
            }
          ],
          "type": "btree",
          "isUnique": true,
          "isPrimary": true
        }
      ],
      "managed": true
    },
    {
      "__className__": "serverpod.TableDefinition",
      "name": "mood_comment_notifications",
      "dartName": "MoodCommentNotification",
      "module": "echomirror_server",
      "schema": "public",
      "columns": [
        {
          "__className__": "serverpod.ColumnDefinition",
          "name": "id",
          "columnType": 6,
          "isNullable": false,
          "columnDefault": "nextval('mood_comment_notifications_id_seq'::regclass)",
          "dartType": "int?"
        },
        {
          "__className__": "serverpod.ColumnDefinition",
          "name": "userId",
          "columnType": 6,
          "isNullable": false,
          "dartType": "int"
        },
        {
          "__className__": "serverpod.ColumnDefinition",
          "name": "moodPinId",
          "columnType": 6,
          "isNullable": false,
          "dartType": "int"
        },
        {
          "__className__": "serverpod.ColumnDefinition",
          "name": "commentId",
          "columnType": 6,
          "isNullable": false,
          "dartType": "int"
        },
        {
          "__className__": "serverpod.ColumnDefinition",
          "name": "commentText",
          "columnType": 0,
          "isNullable": false,
          "dartType": "String"
        },
        {
          "__className__": "serverpod.ColumnDefinition",
          "name": "sentiment",
          "columnType": 0,
          "isNullable": false,
          "dartType": "String"
        },
        {
          "__className__": "serverpod.ColumnDefinition",
          "name": "timestamp",
          "columnType": 4,
          "isNullable": false,
          "dartType": "DateTime"
        },
        {
          "__className__": "serverpod.ColumnDefinition",
          "name": "isRead",
          "columnType": 1,
          "isNullable": false,
          "dartType": "bool"
        }
      ],
      "foreignKeys": [],
      "indexes": [
        {
          "__className__": "serverpod.IndexDefinition",
          "indexName": "mood_comment_notifications_pkey",
          "elements": [
            {
              "__className__": "serverpod.IndexElementDefinition",
              "type": 0,
              "definition": "id"
            }
          ],
          "type": "btree",
          "isUnique": true,
          "isPrimary": true
        },
        {
          "__className__": "serverpod.IndexDefinition",
          "indexName": "mood_notification_user_idx",
          "elements": [
            {
              "__className__": "serverpod.IndexElementDefinition",
              "type": 0,
              "definition": "userId"
            }
          ],
          "type": "btree",
          "isUnique": false,
          "isPrimary": false
        },
        {
          "__className__": "serverpod.IndexDefinition",
          "indexName": "mood_notification_unread_idx",
          "elements": [
            {
              "__className__": "serverpod.IndexElementDefinition",
              "type": 0,
              "definition": "userId"
            },
            {
              "__className__": "serverpod.IndexElementDefinition",
              "type": 0,
              "definition": "isRead"
            }
          ],
          "type": "btree",
          "isUnique": false,
          "isPrimary": false
        },
        {
          "__className__": "serverpod.IndexDefinition",
          "indexName": "mood_notification_timestamp_idx",
          "elements": [
            {
              "__className__": "serverpod.IndexElementDefinition",
              "type": 0,
              "definition": "timestamp"
            }
          ],
          "type": "btree",
          "isUnique": false,
          "isPrimary": false
        }
      ],
      "managed": true
    },
    {
      "__className__": "serverpod.TableDefinition",
      "name": "mood_pin_comments",
      "dartName": "MoodPinComment",
      "module": "echomirror_server",
      "schema": "public",
      "columns": [
        {
          "__className__": "serverpod.ColumnDefinition",
          "name": "id",
          "columnType": 6,
          "isNullable": false,
          "columnDefault": "nextval('mood_pin_comments_id_seq'::regclass)",
          "dartType": "int?"
        },
        {
          "__className__": "serverpod.ColumnDefinition",
          "name": "moodPinId",
          "columnType": 6,
          "isNullable": false,
          "dartType": "int"
        },
        {
          "__className__": "serverpod.ColumnDefinition",
          "name": "userId",
          "columnType": 6,
          "isNullable": true,
          "dartType": "int?"
        },
        {
          "__className__": "serverpod.ColumnDefinition",
          "name": "text",
          "columnType": 0,
          "isNullable": false,
          "dartType": "String"
        },
        {
          "__className__": "serverpod.ColumnDefinition",
          "name": "timestamp",
          "columnType": 4,
          "isNullable": false,
          "dartType": "DateTime"
        }
      ],
      "foreignKeys": [],
      "indexes": [
        {
          "__className__": "serverpod.IndexDefinition",
          "indexName": "mood_pin_comments_pkey",
          "elements": [
            {
              "__className__": "serverpod.IndexElementDefinition",
              "type": 0,
              "definition": "id"
            }
          ],
          "type": "btree",
          "isUnique": true,
          "isPrimary": true
        },
        {
          "__className__": "serverpod.IndexDefinition",
          "indexName": "mood_pin_comment_mood_pin_idx",
          "elements": [
            {
              "__className__": "serverpod.IndexElementDefinition",
              "type": 0,
              "definition": "moodPinId"
            }
          ],
          "type": "btree",
          "isUnique": false,
          "isPrimary": false
        },
        {
          "__className__": "serverpod.IndexDefinition",
          "indexName": "mood_pin_comment_user_idx",
          "elements": [
            {
              "__className__": "serverpod.IndexElementDefinition",
              "type": 0,
              "definition": "userId"
            }
          ],
          "type": "btree",
          "isUnique": false,
          "isPrimary": false
        },
        {
          "__className__": "serverpod.IndexDefinition",
          "indexName": "mood_pin_comment_timestamp_idx",
          "elements": [
            {
              "__className__": "serverpod.IndexElementDefinition",
              "type": 0,
              "definition": "timestamp"
            }
          ],
          "type": "btree",
          "isUnique": false,
          "isPrimary": false
        }
      ],
      "managed": true
    },
    {
      "__className__": "serverpod.TableDefinition",
      "name": "mood_pins",
      "dartName": "MoodPin",
      "module": "echomirror_server",
      "schema": "public",
      "columns": [
        {
          "__className__": "serverpod.ColumnDefinition",
          "name": "id",
          "columnType": 6,
          "isNullable": false,
          "columnDefault": "nextval('mood_pins_id_seq'::regclass)",
          "dartType": "int?"
        },
        {
          "__className__": "serverpod.ColumnDefinition",
          "name": "sentiment",
          "columnType": 0,
          "isNullable": false,
          "dartType": "String"
        },
        {
          "__className__": "serverpod.ColumnDefinition",
          "name": "gridLat",
          "columnType": 3,
          "isNullable": false,
          "dartType": "double"
        },
        {
          "__className__": "serverpod.ColumnDefinition",
          "name": "gridLon",
          "columnType": 3,
          "isNullable": false,
          "dartType": "double"
        },
        {
          "__className__": "serverpod.ColumnDefinition",
          "name": "timestamp",
          "columnType": 4,
          "isNullable": false,
          "dartType": "DateTime"
        },
        {
          "__className__": "serverpod.ColumnDefinition",
          "name": "expiresAt",
          "columnType": 4,
          "isNullable": true,
          "dartType": "DateTime?"
        }
      ],
      "foreignKeys": [],
      "indexes": [
        {
          "__className__": "serverpod.IndexDefinition",
          "indexName": "mood_pins_pkey",
          "elements": [
            {
              "__className__": "serverpod.IndexElementDefinition",
              "type": 0,
              "definition": "id"
            }
          ],
          "type": "btree",
          "isUnique": true,
          "isPrimary": true
        },
        {
          "__className__": "serverpod.IndexDefinition",
          "indexName": "mood_pin_timestamp_idx",
          "elements": [
            {
              "__className__": "serverpod.IndexElementDefinition",
              "type": 0,
              "definition": "timestamp"
            }
          ],
          "type": "btree",
          "isUnique": false,
          "isPrimary": false
        },
        {
          "__className__": "serverpod.IndexDefinition",
          "indexName": "mood_pin_expires_idx",
          "elements": [
            {
              "__className__": "serverpod.IndexElementDefinition",
              "type": 0,
              "definition": "expiresAt"
            }
          ],
          "type": "btree",
          "isUnique": false,
          "isPrimary": false
        }
      ],
      "managed": true
    },
    {
      "__className__": "serverpod.TableDefinition",
      "name": "scheduled_sessions",
      "dartName": "ScheduledSession",
      "module": "echomirror_server",
      "schema": "public",
      "columns": [
        {
          "__className__": "serverpod.ColumnDefinition",
          "name": "id",
          "columnType": 6,
          "isNullable": false,
          "columnDefault": "nextval('scheduled_sessions_id_seq'::regclass)",
          "dartType": "int?"
        },
        {
          "__className__": "serverpod.ColumnDefinition",
          "name": "hostId",
          "columnType": 0,
          "isNullable": false,
          "dartType": "String"
        },
        {
          "__className__": "serverpod.ColumnDefinition",
          "name": "hostName",
          "columnType": 0,
          "isNullable": false,
          "dartType": "String"
        },
        {
          "__className__": "serverpod.ColumnDefinition",
          "name": "hostAvatarUrl",
          "columnType": 0,
          "isNullable": true,
          "dartType": "String?"
        },
        {
          "__className__": "serverpod.ColumnDefinition",
          "name": "title",
          "columnType": 0,
          "isNullable": false,
          "dartType": "String"
        },
        {
          "__className__": "serverpod.ColumnDefinition",
          "name": "description",
          "columnType": 0,
          "isNullable": true,
          "dartType": "String?"
        },
        {
          "__className__": "serverpod.ColumnDefinition",
          "name": "scheduledTime",
          "columnType": 4,
          "isNullable": false,
          "dartType": "DateTime"
        },
        {
          "__className__": "serverpod.ColumnDefinition",
          "name": "createdAt",
          "columnType": 4,
          "isNullable": false,
          "dartType": "DateTime"
        },
        {
          "__className__": "serverpod.ColumnDefinition",
          "name": "isVideoEnabled",
          "columnType": 1,
          "isNullable": false,
          "dartType": "bool"
        },
        {
          "__className__": "serverpod.ColumnDefinition",
          "name": "isVoiceOnly",
          "columnType": 1,
          "isNullable": false,
          "dartType": "bool"
        },
        {
          "__className__": "serverpod.ColumnDefinition",
          "name": "isNotified",
          "columnType": 1,
          "isNullable": false,
          "columnDefault": "false",
          "dartType": "bool"
        },
        {
          "__className__": "serverpod.ColumnDefinition",
          "name": "isCancelled",
          "columnType": 1,
          "isNullable": false,
          "columnDefault": "false",
          "dartType": "bool"
        },
        {
          "__className__": "serverpod.ColumnDefinition",
          "name": "actualSessionId",
          "columnType": 0,
          "isNullable": true,
          "dartType": "String?"
        }
      ],
      "foreignKeys": [],
      "indexes": [
        {
          "__className__": "serverpod.IndexDefinition",
          "indexName": "scheduled_sessions_pkey",
          "elements": [
            {
              "__className__": "serverpod.IndexElementDefinition",
              "type": 0,
              "definition": "id"
            }
          ],
          "type": "btree",
          "isUnique": true,
          "isPrimary": true
        },
        {
          "__className__": "serverpod.IndexDefinition",
          "indexName": "scheduled_time_idx",
          "elements": [
            {
              "__className__": "serverpod.IndexElementDefinition",
              "type": 0,
              "definition": "scheduledTime"
            }
          ],
          "type": "btree",
          "isUnique": false,
          "isPrimary": false
        },
        {
          "__className__": "serverpod.IndexDefinition",
          "indexName": "scheduled_host_id_idx",
          "elements": [
            {
              "__className__": "serverpod.IndexElementDefinition",
              "type": 0,
              "definition": "hostId"
            }
          ],
          "type": "btree",
          "isUnique": false,
          "isPrimary": false
        },
        {
          "__className__": "serverpod.IndexDefinition",
          "indexName": "is_notified_idx",
          "elements": [
            {
              "__className__": "serverpod.IndexElementDefinition",
              "type": 0,
              "definition": "isNotified"
            }
          ],
          "type": "btree",
          "isUnique": false,
          "isPrimary": false
        }
      ],
      "managed": true
    },
    {
      "__className__": "serverpod.TableDefinition",
      "name": "user_mood_pins",
      "dartName": "UserMoodPin",
      "module": "echomirror_server",
      "schema": "public",
      "columns": [
        {
          "__className__": "serverpod.ColumnDefinition",
          "name": "id",
          "columnType": 6,
          "isNullable": false,
          "columnDefault": "nextval('user_mood_pins_id_seq'::regclass)",
          "dartType": "int?"
        },
        {
          "__className__": "serverpod.ColumnDefinition",
          "name": "userId",
          "columnType": 6,
          "isNullable": false,
          "dartType": "int"
        },
        {
          "__className__": "serverpod.ColumnDefinition",
          "name": "moodPinId",
          "columnType": 6,
          "isNullable": false,
          "dartType": "int"
        },
        {
          "__className__": "serverpod.ColumnDefinition",
          "name": "createdAt",
          "columnType": 4,
          "isNullable": false,
          "dartType": "DateTime"
        }
      ],
      "foreignKeys": [],
      "indexes": [
        {
          "__className__": "serverpod.IndexDefinition",
          "indexName": "user_mood_pins_pkey",
          "elements": [
            {
              "__className__": "serverpod.IndexElementDefinition",
              "type": 0,
              "definition": "id"
            }
          ],
          "type": "btree",
          "isUnique": true,
          "isPrimary": true
        },
        {
          "__className__": "serverpod.IndexDefinition",
          "indexName": "user_mood_pin_user_idx",
          "elements": [
            {
              "__className__": "serverpod.IndexElementDefinition",
              "type": 0,
              "definition": "userId"
            }
          ],
          "type": "btree",
          "isUnique": false,
          "isPrimary": false
        },
        {
          "__className__": "serverpod.IndexDefinition",
          "indexName": "user_mood_pin_mood_pin_idx",
          "elements": [
            {
              "__className__": "serverpod.IndexElementDefinition",
              "type": 0,
              "definition": "moodPinId"
            }
          ],
          "type": "btree",
          "isUnique": false,
          "isPrimary": false
        },
        {
          "__className__": "serverpod.IndexDefinition",
          "indexName": "user_mood_pin_unique_idx",
          "elements": [
            {
              "__className__": "serverpod.IndexElementDefinition",
              "type": 0,
              "definition": "userId"
            },
            {
              "__className__": "serverpod.IndexElementDefinition",
              "type": 0,
              "definition": "moodPinId"
            }
          ],
          "type": "btree",
          "isUnique": true,
          "isPrimary": false
        }
      ],
      "managed": true
    },
    {
      "__className__": "serverpod.TableDefinition",
      "name": "video_posts",
      "dartName": "VideoPost",
      "module": "echomirror_server",
      "schema": "public",
      "columns": [
        {
          "__className__": "serverpod.ColumnDefinition",
          "name": "id",
          "columnType": 6,
          "isNullable": false,
          "columnDefault": "nextval('video_posts_id_seq'::regclass)",
          "dartType": "int?"
        },
        {
          "__className__": "serverpod.ColumnDefinition",
          "name": "videoUrl",
          "columnType": 0,
          "isNullable": false,
          "dartType": "String"
        },
        {
          "__className__": "serverpod.ColumnDefinition",
          "name": "moodTag",
          "columnType": 0,
          "isNullable": false,
          "dartType": "String"
        },
        {
          "__className__": "serverpod.ColumnDefinition",
          "name": "timestamp",
          "columnType": 4,
          "isNullable": false,
          "dartType": "DateTime"
        },
        {
          "__className__": "serverpod.ColumnDefinition",
          "name": "expiresAt",
          "columnType": 4,
          "isNullable": false,
          "dartType": "DateTime"
        }
      ],
      "foreignKeys": [],
      "indexes": [
        {
          "__className__": "serverpod.IndexDefinition",
          "indexName": "video_posts_pkey",
          "elements": [
            {
              "__className__": "serverpod.IndexElementDefinition",
              "type": 0,
              "definition": "id"
            }
          ],
          "type": "btree",
          "isUnique": true,
          "isPrimary": true
        },
        {
          "__className__": "serverpod.IndexDefinition",
          "indexName": "video_post_timestamp_idx",
          "elements": [
            {
              "__className__": "serverpod.IndexElementDefinition",
              "type": 0,
              "definition": "timestamp"
            }
          ],
          "type": "btree",
          "isUnique": false,
          "isPrimary": false
        },
        {
          "__className__": "serverpod.IndexDefinition",
          "indexName": "video_post_expires_idx",
          "elements": [
            {
              "__className__": "serverpod.IndexElementDefinition",
              "type": 0,
              "definition": "expiresAt"
            }
          ],
          "type": "btree",
          "isUnique": false,
          "isPrimary": false
        }
      ],
      "managed": true
    },
    {
      "__className__": "serverpod.TableDefinition",
      "name": "video_sessions",
      "dartName": "VideoSession",
      "module": "echomirror_server",
      "schema": "public",
      "columns": [
        {
          "__className__": "serverpod.ColumnDefinition",
          "name": "id",
          "columnType": 6,
          "isNullable": false,
          "columnDefault": "nextval('video_sessions_id_seq'::regclass)",
          "dartType": "int?"
        },
        {
          "__className__": "serverpod.ColumnDefinition",
          "name": "hostId",
          "columnType": 0,
          "isNullable": false,
          "dartType": "String"
        },
        {
          "__className__": "serverpod.ColumnDefinition",
          "name": "hostName",
          "columnType": 0,
          "isNullable": false,
          "dartType": "String"
        },
        {
          "__className__": "serverpod.ColumnDefinition",
          "name": "hostAvatarUrl",
          "columnType": 0,
          "isNullable": true,
          "dartType": "String?"
        },
        {
          "__className__": "serverpod.ColumnDefinition",
          "name": "title",
          "columnType": 0,
          "isNullable": false,
          "dartType": "String"
        },
        {
          "__className__": "serverpod.ColumnDefinition",
          "name": "createdAt",
          "columnType": 4,
          "isNullable": false,
          "dartType": "DateTime"
        },
        {
          "__className__": "serverpod.ColumnDefinition",
          "name": "expiresAt",
          "columnType": 4,
          "isNullable": false,
          "dartType": "DateTime"
        },
        {
          "__className__": "serverpod.ColumnDefinition",
          "name": "participantCount",
          "columnType": 6,
          "isNullable": false,
          "dartType": "int"
        },
        {
          "__className__": "serverpod.ColumnDefinition",
          "name": "isVideoEnabled",
          "columnType": 1,
          "isNullable": false,
          "dartType": "bool"
        },
        {
          "__className__": "serverpod.ColumnDefinition",
          "name": "isVoiceOnly",
          "columnType": 1,
          "isNullable": false,
          "dartType": "bool"
        },
        {
          "__className__": "serverpod.ColumnDefinition",
          "name": "isActive",
          "columnType": 1,
          "isNullable": false,
          "dartType": "bool"
        }
      ],
      "foreignKeys": [],
      "indexes": [
        {
          "__className__": "serverpod.IndexDefinition",
          "indexName": "video_sessions_pkey",
          "elements": [
            {
              "__className__": "serverpod.IndexElementDefinition",
              "type": 0,
              "definition": "id"
            }
          ],
          "type": "btree",
          "isUnique": true,
          "isPrimary": true
        },
        {
          "__className__": "serverpod.IndexDefinition",
          "indexName": "created_at_idx",
          "elements": [
            {
              "__className__": "serverpod.IndexElementDefinition",
              "type": 0,
              "definition": "createdAt"
            }
          ],
          "type": "btree",
          "isUnique": false,
          "isPrimary": false
        },
        {
          "__className__": "serverpod.IndexDefinition",
          "indexName": "expires_at_idx",
          "elements": [
            {
              "__className__": "serverpod.IndexElementDefinition",
              "type": 0,
              "definition": "expiresAt"
            }
          ],
          "type": "btree",
          "isUnique": false,
          "isPrimary": false
        },
        {
          "__className__": "serverpod.IndexDefinition",
          "indexName": "is_active_idx",
          "elements": [
            {
              "__className__": "serverpod.IndexElementDefinition",
              "type": 0,
              "definition": "isActive"
            }
          ],
          "type": "btree",
          "isUnique": false,
          "isPrimary": false
        },
        {
          "__className__": "serverpod.IndexDefinition",
          "indexName": "host_id_idx",
          "elements": [
            {
              "__className__": "serverpod.IndexElementDefinition",
              "type": 0,
              "definition": "hostId"
            }
          ],
          "type": "btree",
          "isUnique": false,
          "isPrimary": false
        }
      ],
      "managed": true
    }
  ],
  "installedModules": [
    {
      "__className__": "serverpod.DatabaseMigrationVersion",
      "module": "serverpod",
      "version": "20251208110333922-v3-0-0"
    },
    {
      "__className__": "serverpod.DatabaseMigrationVersion",
      "module": "serverpod_auth_idp",
      "version": "20251208110420531-v3-0-0"
    },
    {
      "__className__": "serverpod.DatabaseMigrationVersion",
      "module": "serverpod_auth_core",
      "version": "20251208110412389-v3-0-0"
    }
  ],
  "migrationApiVersion": 1
}